[{
  "_id": {
    "$oid": "6394cee51b13ff7ad5e89d6a"
  },
  "name": "Shirt",
  "price": 30,
  "discPrice": 30,
  "category": 1,
  "subCategory": 1,
  "material": "Cotton",
  "detail": "Blue Jeans shirt for Men",
  "imageUrl": "cat1iag2.jpg",
  "createdDate": {
    "$date": {
      "$numberLong": "1670696677411"
    }
  },
  "__v": 0
},{
  "_id": {
    "$oid": "6394cf2d1b13ff7ad5e89d6c"
  },
  "name": "T-Shirt",
  "price": 20,
  "discPrice": 20,
  "category": 1,
  "subCategory": 1,
  "material": "Mix Marial",
  "detail": "Black T-Shirt for Men",
  "imageUrl": "cat1imag1.jpg",
  "createdDate": {
    "$date": {
      "$numberLong": "1670696749437"
    }
  },
  "__v": 0
},{
  "_id": {
    "$oid": "6394cfdc1b13ff7ad5e89d6e"
  },
  "name": "T-Shirt",
  "price": 20,
  "discPrice": 20,
  "category": 1,
  "subCategory": 1,
  "material": "Mix Cotton",
  "detail": "Blue and white T-Shirt for Men",
  "imageUrl": "cat1imag2.jpg",
  "createdDate": {
    "$date": {
      "$numberLong": "1670696924907"
    }
  },
  "__v": 0
},{
  "_id": {
    "$oid": "6394d0381b13ff7ad5e89d70"
  },
  "name": "Shirt",
  "price": 30,
  "discPrice": 30,
  "category": 1,
  "subCategory": 1,
  "material": "Mix Matrial",
  "detail": "Plain red shirt for Men",
  "imageUrl": "cat1imag3.jpg",
  "createdDate": {
    "$date": {
      "$numberLong": "1670697016069"
    }
  },
  "__v": 0
},{
  "_id": {
    "$oid": "6394d0801b13ff7ad5e89d72"
  },
  "name": "Shirt",
  "price": 40,
  "discPrice": 40,
  "category": 1,
  "subCategory": 1,
  "material": "Mix Matrial",
  "detail": "Plain red shirt with white dots.",
  "imageUrl": "cat1imag4.jpg",
  "createdDate": {
    "$date": {
      "$numberLong": "1670697088098"
    }
  },
  "__v": 0
},{
  "_id": {
    "$oid": "6394d0b51b13ff7ad5e89d74"
  },
  "name": "Shirt",
  "price": 70,
  "discPrice": 40,
  "category": 1,
  "subCategory": 1,
  "material": "Pure Cotton",
  "detail": "Black and blue vertical lines",
  "imageUrl": "cat1imag5.jpg",
  "createdDate": {
    "$date": {
      "$numberLong": "1670697141568"
    }
  },
  "__v": 0
},{
  "_id": {
    "$oid": "6394d1901b13ff7ad5e89d77"
  },
  "name": "Pents",
  "price": 100,
  "discPrice": 100,
  "category": 1,
  "subCategory": 2,
  "material": "Pure Cotton",
  "detail": "Blue cotton genes",
  "imageUrl": "menpent01.jpg",
  "createdDate": {
    "$date": {
      "$numberLong": "1670697360360"
    }
  },
  "__v": 0
},{
  "_id": {
    "$oid": "6394d1c11b13ff7ad5e89d79"
  },
  "name": "Pents",
  "price": 75,
  "discPrice": 75,
  "category": 1,
  "subCategory": 2,
  "material": "Pure Cotton",
  "detail": "Plain black dress pent",
  "imageUrl": "menpent02.jpg",
  "createdDate": {
    "$date": {
      "$numberLong": "1670697409156"
    }
  },
  "__v": 0
},{
  "_id": {
    "$oid": "6394d1f01b13ff7ad5e89d7b"
  },
  "name": "Pents",
  "price": 120,
  "discPrice": 120,
  "category": 1,
  "subCategory": 2,
  "material": "Pure Cotton",
  "detail": "Men Formal Jeans",
  "imageUrl": "menpent03.jpg",
  "createdDate": {
    "$date": {
      "$numberLong": "1670697456097"
    }
  },
  "__v": 0
},{
  "_id": {
    "$oid": "6394d2231b13ff7ad5e89d7d"
  },
  "name": "Pents",
  "price": 130,
  "discPrice": 130,
  "category": 1,
  "subCategory": 2,
  "material": "Pure Cotton",
  "detail": "Blue funcky style Jeans",
  "imageUrl": "menpent04.jpg",
  "createdDate": {
    "$date": {
      "$numberLong": "1670697507398"
    }
  },
  "__v": 0
},{
  "_id": {
    "$oid": "6394d2521b13ff7ad5e89d7f"
  },
  "name": "Pents",
  "price": 120,
  "discPrice": 120,
  "category": 1,
  "subCategory": 2,
  "material": "Jeans",
  "detail": "Formal Jeans",
  "imageUrl": "menpent05.jpg",
  "createdDate": {
    "$date": {
      "$numberLong": "1670697554030"
    }
  },
  "__v": 0
},{
  "_id": {
    "$oid": "6394d27e1b13ff7ad5e89d81"
  },
  "name": "Pents",
  "price": 120,
  "discPrice": 120,
  "category": 1,
  "subCategory": 2,
  "material": "Jeans",
  "detail": "Ligh Blue For Men",
  "imageUrl": "menpent06.jpg",
  "createdDate": {
    "$date": {
      "$numberLong": "1670697598231"
    }
  },
  "__v": 0
},{
  "_id": {
    "$oid": "6394d2dd1b13ff7ad5e89d83"
  },
  "name": "Pents",
  "price": 120,
  "discPrice": 120,
  "category": 1,
  "subCategory": 2,
  "material": "Jeans",
  "detail": "Men Jeans for casual wear",
  "imageUrl": "menpent07.jpg",
  "createdDate": {
    "$date": {
      "$numberLong": "1670697693034"
    }
  },
  "__v": 0
},{
  "_id": {
    "$oid": "6394d46d1b13ff7ad5e89d8b"
  },
  "name": "Shoes",
  "price": 120,
  "discPrice": 120,
  "category": 1,
  "subCategory": 3,
  "material": "Leather",
  "detail": "Men Blue for casual wear",
  "imageUrl": "mehshoe01.jpg",
  "createdDate": {
    "$date": {
      "$numberLong": "1670698093126"
    }
  },
  "__v": 0
},{
  "_id": {
    "$oid": "6394d4c21b13ff7ad5e89d8d"
  },
  "name": "Shoes",
  "price": 75,
  "discPrice": 75,
  "category": 1,
  "subCategory": 3,
  "material": "Leather",
  "detail": "Brown for men",
  "imageUrl": "mehshoe02.jpg",
  "createdDate": {
    "$date": {
      "$numberLong": "1670698178764"
    }
  },
  "__v": 0
},{
  "_id": {
    "$oid": "6394d5031b13ff7ad5e89d8f"
  },
  "name": "Shoes",
  "price": 125,
  "discPrice": 125,
  "category": 1,
  "subCategory": 3,
  "material": "Leather",
  "detail": "Orange for men",
  "imageUrl": "mehshoe03.jpg",
  "createdDate": {
    "$date": {
      "$numberLong": "1670698243060"
    }
  },
  "__v": 0
},{
  "_id": {
    "$oid": "6394d5291b13ff7ad5e89d91"
  },
  "name": "Shoes",
  "price": 125,
  "discPrice": 125,
  "category": 1,
  "subCategory": 3,
  "material": "Leather",
  "detail": "Funcky for men",
  "imageUrl": "mehshoe04.jpg",
  "createdDate": {
    "$date": {
      "$numberLong": "1670698281173"
    }
  },
  "__v": 0
},{
  "_id": {
    "$oid": "6394d55b1b13ff7ad5e89d93"
  },
  "name": "Shoes",
  "price": 175,
  "discPrice": 175,
  "category": 1,
  "subCategory": 3,
  "material": "Leather",
  "detail": "Bule Shine Shoe for men",
  "imageUrl": "mehshoe05.jpg",
  "createdDate": {
    "$date": {
      "$numberLong": "1670698331710"
    }
  },
  "__v": 0
},{
  "_id": {
    "$oid": "6394d5841b13ff7ad5e89d95"
  },
  "name": "Shoes",
  "price": 315,
  "discPrice": 315,
  "category": 1,
  "subCategory": 3,
  "material": "Leather",
  "detail": "Grey Joggers",
  "imageUrl": "mehshoe06.jpg",
  "createdDate": {
    "$date": {
      "$numberLong": "1670698372562"
    }
  },
  "__v": 0
},{
  "_id": {
    "$oid": "6394d6c01b13ff7ad5e89d98"
  },
  "name": "SUITE",
  "price": 600,
  "discPrice": 600,
  "category": 1,
  "subCategory": 4,
  "material": "Light weight",
  "detail": "Brown casual suit for men",
  "imageUrl": "mekot01.jpg",
  "createdDate": {
    "$date": {
      "$numberLong": "1670698688161"
    }
  },
  "__v": 0
},{
  "_id": {
    "$oid": "6394d6e01b13ff7ad5e89d9a"
  },
  "name": "SUITE",
  "price": 850,
  "discPrice": 850,
  "category": 1,
  "subCategory": 4,
  "material": "Light weight",
  "detail": "Brown casual suit for men",
  "imageUrl": "mekot02.jpg",
  "createdDate": {
    "$date": {
      "$numberLong": "1670698720915"
    }
  },
  "__v": 0
},{
  "_id": {
    "$oid": "6394d6f51b13ff7ad5e89d9c"
  },
  "name": "SUITE",
  "price": 930,
  "discPrice": 930,
  "category": 1,
  "subCategory": 4,
  "material": "Light weight",
  "detail": "Blue casual suit for men",
  "imageUrl": "mekot03.jpg",
  "createdDate": {
    "$date": {
      "$numberLong": "1670698741107"
    }
  },
  "__v": 0
},{
  "_id": {
    "$oid": "6394d72c1b13ff7ad5e89d9e"
  },
  "name": "SUITE",
  "price": 1100,
  "discPrice": 1100,
  "category": 1,
  "subCategory": 4,
  "material": "Quality Stuff",
  "detail": "Brown dotted casual suit for men",
  "imageUrl": "mekot04.jpg",
  "createdDate": {
    "$date": {
      "$numberLong": "1670698796710"
    }
  },
  "__v": 0
},{
  "_id": {
    "$oid": "6394d7671b13ff7ad5e89da0"
  },
  "name": "SUITE",
  "price": 1100,
  "discPrice": 1100,
  "category": 1,
  "subCategory": 4,
  "material": "Stylish",
  "detail": "Sea Green Stylish suit for men",
  "imageUrl": "mekot05.jpg",
  "createdDate": {
    "$date": {
      "$numberLong": "1670698855512"
    }
  },
  "__v": 0
},{
  "_id": {
    "$oid": "6394d7841b13ff7ad5e89da2"
  },
  "name": "SUITE",
  "price": 650,
  "discPrice": 650,
  "category": 1,
  "subCategory": 4,
  "material": "Stylish",
  "detail": "Patry suit for men",
  "imageUrl": "mekot06.jpg",
  "createdDate": {
    "$date": {
      "$numberLong": "1670698884454"
    }
  },
  "__v": 0
},{
  "_id": {
    "$oid": "6394da045a37ed2878069dbf"
  },
  "name": "MEN TIE",
  "price": 20,
  "discPrice": 20,
  "category": 1,
  "subCategory": 5,
  "material": "Silk",
  "detail": "Yellow tie with lining",
  "imageUrl": "Tie0.jpg",
  "createdDate": {
    "$date": {
      "$numberLong": "1670699524882"
    }
  },
  "__v": 0
},{
  "_id": {
    "$oid": "6394da3f5a37ed2878069dc1"
  },
  "name": "MEN TIE",
  "price": 35,
  "discPrice": 35,
  "category": 1,
  "subCategory": 5,
  "material": "Silk",
  "detail": "Blue and white tie",
  "imageUrl": "Tie01.jpg",
  "createdDate": {
    "$date": {
      "$numberLong": "1670699583950"
    }
  },
  "__v": 0
},{
  "_id": {
    "$oid": "6394da655a37ed2878069dc4"
  },
  "name": "MEN TIE",
  "price": 40,
  "discPrice": 40,
  "category": 1,
  "subCategory": 5,
  "material": "Silk",
  "detail": "Pure Black tie",
  "imageUrl": "Tie02.jpg",
  "createdDate": {
    "$date": {
      "$numberLong": "1670699621696"
    }
  },
  "__v": 0
},{
  "_id": {
    "$oid": "6394da995a37ed2878069dc6"
  },
  "name": "MEN TIE",
  "price": 50,
  "discPrice": 50,
  "category": 1,
  "subCategory": 5,
  "material": "Silk",
  "detail": "Orange and Brown lining tie",
  "imageUrl": "Tie03.jpg",
  "createdDate": {
    "$date": {
      "$numberLong": "1670699673156"
    }
  },
  "__v": 0
},{
  "_id": {
    "$oid": "6394dac55a37ed2878069dc8"
  },
  "name": "MEN TIE",
  "price": 35,
  "discPrice": 35,
  "category": 1,
  "subCategory": 5,
  "material": "Silk",
  "detail": "Sky Blue tie",
  "imageUrl": "Tie04.jpg",
  "createdDate": {
    "$date": {
      "$numberLong": "1670699717318"
    }
  },
  "__v": 0
},{
  "_id": {
    "$oid": "6394daec5a37ed2878069dca"
  },
  "name": "MEN TIE",
  "price": 75,
  "discPrice": 75,
  "category": 1,
  "subCategory": 5,
  "material": "Silk",
  "detail": "Royal Blue stylish tie",
  "imageUrl": "Tie05.jpg",
  "createdDate": {
    "$date": {
      "$numberLong": "1670699756699"
    }
  },
  "__v": 0
},{
  "_id": {
    "$oid": "6394db115a37ed2878069dcc"
  },
  "name": "MEN TIE",
  "price": 65,
  "discPrice": 65,
  "category": 1,
  "subCategory": 5,
  "material": "Silk",
  "detail": "Green Texture tie",
  "imageUrl": "Tie06.jpg",
  "createdDate": {
    "$date": {
      "$numberLong": "1670699793602"
    }
  },
  "__v": 0
},{
  "_id": {
    "$oid": "6394e2015a37ed2878069dd3"
  },
  "name": "Women Pent",
  "price": 100,
  "discPrice": 100,
  "category": 2,
  "subCategory": 1,
  "material": "Cotton",
  "detail": "Women Pent for casual wear",
  "imageUrl": "femailpent03.jpg",
  "createdDate": {
    "$date": {
      "$numberLong": "1670701569792"
    }
  },
  "__v": 0
},{
  "_id": {
    "$oid": "6394e2365a37ed2878069dd5"
  },
  "name": "Women Pent",
  "price": 85,
  "discPrice": 85,
  "category": 2,
  "subCategory": 1,
  "material": "Cotton",
  "detail": "Green Pent for casual wear",
  "imageUrl": "femailpent04.jpg",
  "createdDate": {
    "$date": {
      "$numberLong": "1670701622446"
    }
  },
  "__v": 0
},{
  "_id": {
    "$oid": "6394e25f5a37ed2878069dd7"
  },
  "name": "Women Pent",
  "price": 28,
  "discPrice": 28,
  "category": 2,
  "subCategory": 1,
  "material": "Cotton",
  "detail": "Gray Pent for casual wear",
  "imageUrl": "femailpent05.jpg",
  "createdDate": {
    "$date": {
      "$numberLong": "1670701663638"
    }
  },
  "__v": 0
},{
  "_id": {
    "$oid": "6394e2705a37ed2878069dd9"
  },
  "name": "Women Pent",
  "price": 35,
  "discPrice": 35,
  "category": 2,
  "subCategory": 1,
  "material": "Cotton",
  "detail": "Red Pent for casual wear",
  "imageUrl": "femailpent06.jpg",
  "createdDate": {
    "$date": {
      "$numberLong": "1670701680438"
    }
  },
  "__v": 0
},{
  "_id": {
    "$oid": "6394e28d5a37ed2878069ddb"
  },
  "name": "Women Pent",
  "price": 54,
  "discPrice": 35,
  "category": 2,
  "subCategory": 1,
  "material": "Cotton",
  "detail": " Pent for formal wear",
  "imageUrl": "femailpent07.jpg",
  "createdDate": {
    "$date": {
      "$numberLong": "1670701709604"
    }
  },
  "__v": 0
},{
  "_id": {
    "$oid": "6394e2ee5a37ed2878069ddd"
  },
  "name": "Women Shirts",
  "price": 54,
  "discPrice": 35,
  "category": 2,
  "subCategory": 2,
  "material": "Cotton",
  "detail": " Green Checked for women",
  "imageUrl": "femailshirt07.jpg",
  "createdDate": {
    "$date": {
      "$numberLong": "1670701806086"
    }
  },
  "__v": 0
},{
  "_id": {
    "$oid": "6394e3055a37ed2878069ddf"
  },
  "name": "Women Shirts",
  "price": 54,
  "discPrice": 35,
  "category": 2,
  "subCategory": 2,
  "material": "Cotton",
  "detail": " Green and black Checked for women",
  "imageUrl": "femailshirt06.jpg",
  "createdDate": {
    "$date": {
      "$numberLong": "1670701829415"
    }
  },
  "__v": 0
},{
  "_id": {
    "$oid": "6394e3285a37ed2878069de1"
  },
  "name": "Women Shirts",
  "price": 125,
  "discPrice": 35,
  "category": 2,
  "subCategory": 2,
  "material": "Cotton",
  "detail": " Red plain for women",
  "imageUrl": "femailshirt05.jpg",
  "createdDate": {
    "$date": {
      "$numberLong": "1670701864676"
    }
  },
  "__v": 0
},{
  "_id": {
    "$oid": "6394e35b5a37ed2878069de3"
  },
  "name": "Women Shirts",
  "price": 125,
  "discPrice": 35,
  "category": 2,
  "subCategory": 2,
  "material": "Cotton",
  "detail": " Sky bluew plain shirt",
  "imageUrl": "femailshirt04.jpg",
  "createdDate": {
    "$date": {
      "$numberLong": "1670701915785"
    }
  },
  "__v": 0
},{
  "_id": {
    "$oid": "6394e3775a37ed2878069de5"
  },
  "name": "Women Shirts",
  "price": 125,
  "discPrice": 35,
  "category": 2,
  "subCategory": 2,
  "material": "Cotton",
  "detail": " Black plain shirt",
  "imageUrl": "femailshirt02.jpg",
  "createdDate": {
    "$date": {
      "$numberLong": "1670701943494"
    }
  },
  "__v": 0
},{
  "_id": {
    "$oid": "6394e38f5a37ed2878069de7"
  },
  "name": "Women Shirts",
  "price": 90,
  "discPrice": 35,
  "category": 2,
  "subCategory": 2,
  "material": "Cotton",
  "detail": " LightGreen plain shirt",
  "imageUrl": "femailshirt01.jpg",
  "createdDate": {
    "$date": {
      "$numberLong": "1670701967438"
    }
  },
  "__v": 0
},{
  "_id": {
    "$oid": "6394e3b65a37ed2878069de9"
  },
  "name": "Women Shirts",
  "price": 125,
  "discPrice": 35,
  "category": 2,
  "subCategory": 2,
  "material": "Cotton",
  "detail": " Hot Ret casual plain shirt",
  "imageUrl": "femailpent01.jpg",
  "createdDate": {
    "$date": {
      "$numberLong": "1670702006757"
    }
  },
  "__v": 0
},{
  "_id": {
    "$oid": "6394e5175a37ed2878069ded"
  },
  "name": "Women Bags",
  "price": 125,
  "discPrice": 35,
  "category": 2,
  "subCategory": 3,
  "material": "Leather",
  "detail": "Causal Sholder Carry ",
  "imageUrl": "bag01.jpg",
  "createdDate": {
    "$date": {
      "$numberLong": "1670702359455"
    }
  },
  "__v": 0
},{
  "_id": {
    "$oid": "6394e5285a37ed2878069def"
  },
  "name": "Women Bags",
  "price": 120,
  "discPrice": 35,
  "category": 2,
  "subCategory": 3,
  "material": "Leather",
  "detail": "Red Sholder Carry ",
  "imageUrl": "bag02.jpg",
  "createdDate": {
    "$date": {
      "$numberLong": "1670702376153"
    }
  },
  "__v": 0
},{
  "_id": {
    "$oid": "6394e5455a37ed2878069df1"
  },
  "name": "Women Bags",
  "price": 120,
  "discPrice": 35,
  "category": 2,
  "subCategory": 3,
  "material": "Leather",
  "detail": "Sky Blue hand carry ",
  "imageUrl": "bag03.jpg",
  "createdDate": {
    "$date": {
      "$numberLong": "1670702405094"
    }
  },
  "__v": 0
},{
  "_id": {
    "$oid": "6394e55d5a37ed2878069df3"
  },
  "name": "Women Bags",
  "price": 85,
  "discPrice": 35,
  "category": 2,
  "subCategory": 3,
  "material": "Leather",
  "detail": "Casual carry ",
  "imageUrl": "bag04.jpg",
  "createdDate": {
    "$date": {
      "$numberLong": "1670702429821"
    }
  },
  "__v": 0
},{
  "_id": {
    "$oid": "6394e5975a37ed2878069df5"
  },
  "name": "Women Bags",
  "price": 50,
  "discPrice": 35,
  "category": 2,
  "subCategory": 3,
  "material": "Leather",
  "detail": "Hot Red fancy carry ",
  "imageUrl": "bag05.jpg",
  "createdDate": {
    "$date": {
      "$numberLong": "1670702487862"
    }
  },
  "__v": 0
},{
  "_id": {
    "$oid": "6394e5b65a37ed2878069df7"
  },
  "name": "Women Bags",
  "price": 110,
  "discPrice": 35,
  "category": 2,
  "subCategory": 3,
  "material": "Leather",
  "detail": "purple fancy carry ",
  "imageUrl": "bag06.jpg",
  "createdDate": {
    "$date": {
      "$numberLong": "1670702518414"
    }
  },
  "__v": 0
},{
  "_id": {
    "$oid": "6394e5d25a37ed2878069df9"
  },
  "name": "Women Bags",
  "price": 125,
  "discPrice": 35,
  "category": 2,
  "subCategory": 3,
  "material": "Leather",
  "detail": "formal carry ",
  "imageUrl": "bag07.jpg",
  "createdDate": {
    "$date": {
      "$numberLong": "1670702546188"
    }
  },
  "__v": 0
},{
  "_id": {
    "$oid": "6394e6265a37ed2878069dfb"
  },
  "name": "Women Bags",
  "price": 44,
  "discPrice": 35,
  "category": 2,
  "subCategory": 3,
  "material": "Leather",
  "detail": "Pink formal carry ",
  "imageUrl": "bag08.jpg",
  "createdDate": {
    "$date": {
      "$numberLong": "1670702630466"
    }
  },
  "__v": 0
},{
  "_id": {
    "$oid": "6394e6485a37ed2878069dfd"
  },
  "name": "Women Bags",
  "price": 155,
  "discPrice": 35,
  "category": 2,
  "subCategory": 3,
  "material": "Leather",
  "detail": "Black formal carry ",
  "imageUrl": "bag09.jpg",
  "createdDate": {
    "$date": {
      "$numberLong": "1670702664912"
    }
  },
  "__v": 0
},{
  "_id": {
    "$oid": "6394e6575a37ed2878069dff"
  },
  "name": "Women Bags",
  "price": 85,
  "discPrice": 35,
  "category": 2,
  "subCategory": 3,
  "material": "Leather",
  "detail": "formal carry ",
  "imageUrl": "bag10.jpg",
  "createdDate": {
    "$date": {
      "$numberLong": "1670702679947"
    }
  },
  "__v": 0
}]